iAppFlyer/iAppFlyerLogo.jpeg
iAppFlyer/init.py
iAppFlyer/main.py
iAppFlyer-2.0.0.dist-info/METADATA
iAppFlyer-2.0.0.dist-info/WHEEL
iAppFlyer-2.0.0.dist-info/entry_points.txt
iAppFlyer-2.0.0.dist-info/top_level.txt
iAppFlyer-2.0.0.dist-info/RECORD
