Metadata-Version: 2.1
Name: iAppFlyer
Version: 2.0.0
Requires-Dist: Pillow
Requires-Dist: requests
